Metadata-Version: 2.1
Name: perceptron-pypi-dhires9196
Version: 0.0.1
Summary: its a implementaion of perceptron
Home-page: https://github.com/dhires9196/perceptron_pypi
Author: USER_NMAE
Author-email: dhires9196@gmail.com
License: UNKNOWN
Project-URL: Bug Tracker, https://github.com/dhires9196/perceptron_pypi/issues
Platform: UNKNOWN
Classifier: Programming Language :: Python :: 3
Classifier: License :: OSI Approved :: MIT License
Classifier: Operating System :: OS Independent
Requires-Python: >=3.6
License-File: LICENSE
Requires-Dist: numpy
Requires-Dist: tqdm
